[
    {
        "model": "authtoken.token",
        "pk": "fa2eba9be8282d595c997ee5cd49f2ed31f65be1",
        "fields": {
            "user": 1,
            "created": "2020-08-29T13:24:27.172Z"
        }
    },
    {
        "model": "authtoken.token",
        "pk": "fa2eba9be8282d595c997ee5cd49f2ed31f65be2",
        "fields": {
            "user": 2,
            "created": "2020-08-29T13:24:27.172Z"
        }
    },
    {
        "model": "authtoken.token",
        "pk": "fa2eba9be8282d595c997ee5cd49f2ed31f65be3",
        "fields": {
            "user": 3,
            "created": "2020-08-29T13:24:27.172Z"
        }
    },
    {
        "model": "authtoken.token",
        "pk": "fa2eba9be8282d595c997ee5cd49f2ed31f65be4",
        "fields": {
            "user": 4,
            "created": "2020-08-29T13:24:27.172Z"
        }
    },
    {
        "model": "authtoken.token",
        "pk": "fa2eba9be8282d595c997ee5cd49f2ed31f65be5",
        "fields": {
            "user": 5,
            "created": "2020-08-29T13:24:27.172Z"
        }
    },
    {
        "model": "authtoken.token",
        "pk": "fa2eba9be8282d595c997ee5cd49f2ed31f65be6",
        "fields": {
            "user": 6,
            "created": "2020-08-29T13:24:27.172Z"
        }
    },
    {
        "model": "authtoken.token",
        "pk": "fa2eba9be8282d595c997ee5cd49f2ed31f65be7",
        "fields": {
            "user": 7,
            "created": "2020-08-29T13:24:27.172Z"
        }
    },
    {
        "model": "authtoken.token",
        "pk": "fa2eba9be8282d595c997ee5cd49f2ed31f65be8",
        "fields": {
            "user": 8,
            "created": "2020-08-29T13:24:27.172Z"
        }
    },
    {
        "model": "authtoken.token",
        "pk": "fa2eba9be8282d595c997ee5cd49f2ed31f65be9",
        "fields": {
            "user": 9,
            "created": "2020-08-29T13:24:27.172Z"
        }
    },
    {
        "model": "authtoken.token",
        "pk": "fa2eba9be8282d595c997ee5cd49f2ed31f65be10",
        "fields": {
            "user": 10,
            "created": "2020-08-29T13:24:27.172Z"
        }
    }
]